django_sns_view/__init__.py
django_sns_view/py.typed
django_sns_view/tests/__init__.py
django_sns_view/tests/helpers.py
django_sns_view/tests/settings.py
django_sns_view/tests/test_data/__init__.py
django_sns_view/tests/test_data/example.pem
django_sns_view/tests/test_data/notifications.py
django_sns_view/tests/test_utils.py
django_sns_view/tests/test_views.py
django_sns_view/types.py
django_sns_view/utils.py
django_sns_view/views.py
django_sns_view-1.0.1.dist-info/LICENSE
django_sns_view-1.0.1.dist-info/METADATA
django_sns_view-1.0.1.dist-info/WHEEL
django_sns_view-1.0.1.dist-info/RECORD
