Metadata-Version: 2.3
Name: django-sns-view
Version: 1.0.1
Summary: A Django view that can be subscribed to Amazon SNS
License: ISC
Author: thelab
Author-email: thelabdev@thelab.co
Requires-Python: >=3.12
Classifier: License :: OSI Approved
Classifier: Programming Language :: Python :: 3
Classifier: Programming Language :: Python :: 3.12
Classifier: Programming Language :: Python :: 3.13
Requires-Dist: Django (>=4.2)
Requires-Dist: cryptography (>=44.0.2)
Requires-Dist: pydantic (>=2.10.6,<3.0.0)
Requires-Dist: requests (>=2.32.3)
